veelib/__init__.py
veelib/ap_featurization.py
veelib/ap_generation_road_network.py
veelib/ml_utils.py
veelib/ndm_road_segment_utils.py
veelib/road_network_graph.py
veelib/visualization_utils.py
veelib-1.0.8.dist-info/METADATA
veelib-1.0.8.dist-info/WHEEL
veelib-1.0.8.dist-info/top_level.txt
veelib-1.0.8.dist-info/RECORD
