Metadata-Version: 2.1
Name: veelib
Version: 1.0.8
Summary: Vee Library
Home-page: https://github.geo.apple.com/yun-hu/veelib
Author: Yun Hu
Author-email: yun_hu@apple.com
License: Apple Internal
Keywords: PySpark,PIE Spark,Spark
Platform: UNKNOWN
Classifier: Development Status :: 4 - Beta
Requires-Dist: pyspark (==3.2.0)
Requires-Dist: numpy
Requires-Dist: geopy
Requires-Dist: rtree
Requires-Dist: folium
Requires-Dist: swifter
Requires-Dist: shapely
Requires-Dist: scipy
Requires-Dist: networkx
Requires-Dist: matplotlib
Requires-Dist: pyarrow
Requires-Dist: scikit-learn
Requires-Dist: joblib
